colony_adm.py
colony_start.py
colony_wsgi.py
colony/__init__.py
colony/base/__init__.py
colony/base/config.py
colony/base/decorators.py
colony/base/exceptions.py
colony/base/information.py
colony/base/legacy.py
colony/base/loggers.py
colony/base/system.py
colony/base/system.pyi
colony/base/test.py
colony/base/util.py
colony/base/vars.py
colony/base/vars.pyi
colony/config/__init__.py
colony/config/base.py
colony/libs/__init__.py
colony/libs/aes_util.py
colony/libs/aes_util.pyi
colony/libs/bank_util.py
colony/libs/bank_util.pyi
colony/libs/barcode_util.py
colony/libs/barcode_util.pyi
colony/libs/cache_util.py
colony/libs/cache_util.pyi
colony/libs/call_util.py
colony/libs/call_util.pyi
colony/libs/control_util.py
colony/libs/control_util.pyi
colony/libs/country_util.py
colony/libs/country_util.pyi
colony/libs/crypt_util.py
colony/libs/crypt_util.pyi
colony/libs/encode_util.py
colony/libs/encode_util.pyi
colony/libs/file_util.py
colony/libs/file_util.pyi
colony/libs/gtin_util.py
colony/libs/gtin_util.pyi
colony/libs/host_util.py
colony/libs/host_util.pyi
colony/libs/import_util.py
colony/libs/import_util.pyi
colony/libs/lazy_util.py
colony/libs/lazy_util.pyi
colony/libs/list_util.py
colony/libs/list_util.pyi
colony/libs/logging_util.py
colony/libs/logging_util.pyi
colony/libs/map_util.py
colony/libs/map_util.pyi
colony/libs/math_util.py
colony/libs/math_util.pyi
colony/libs/number_util.py
colony/libs/number_util.pyi
colony/libs/object_util.py
colony/libs/object_util.pyi
colony/libs/observer_util.py
colony/libs/observer_util.pyi
colony/libs/os_util.py
colony/libs/os_util.pyi
colony/libs/path_util.py
colony/libs/path_util.pyi
colony/libs/protection_util.py
colony/libs/protection_util.pyi
colony/libs/quote_util.py
colony/libs/quote_util.pyi
colony/libs/round_util.py
colony/libs/round_util.pyi
colony/libs/scheduling_util.py
colony/libs/scheduling_util.pyi
colony/libs/size_util.py
colony/libs/size_util.pyi
colony/libs/stack_util.py
colony/libs/stack_util.pyi
colony-1.4.35.dist-info/METADATA
colony-1.4.35.dist-info/WHEEL
colony-1.4.35.dist-info/entry_points.txt
colony-1.4.35.dist-info/top_level.txt
colony-1.4.35.dist-info/RECORD
